Metadata-Version: 2.4
Name: dominus-sdk-python-dev
Version: 2.1.8
Summary: Python SDK for the Dominus Orchestrator Platform
Author-email: CareBridge Systems <dev@carebridge.io>
License: Proprietary
Project-URL: Homepage, https://github.com/carebridgesystems/dominus-sdk-python
Project-URL: Repository, https://github.com/carebridgesystems/dominus-sdk-python
Keywords: dominus,carebridge,sdk,orchestrator,api,async
Classifier: Development Status :: 4 - Beta
Classifier: Intended Audience :: Developers
Classifier: License :: Other/Proprietary License
Classifier: Operating System :: OS Independent
Classifier: Programming Language :: Python :: 3
Classifier: Programming Language :: Python :: 3.9
Classifier: Programming Language :: Python :: 3.10
Classifier: Programming Language :: Python :: 3.11
Classifier: Programming Language :: Python :: 3.12
Classifier: Topic :: Software Development :: Libraries :: Python Modules
Classifier: Framework :: AsyncIO
Requires-Python: >=3.9
Requires-Dist: httpx>=0.24.0
Requires-Dist: bcrypt>=4.0.0
Requires-Dist: cryptography>=41.0.0
Provides-Extra: jwt
Requires-Dist: PyJWT>=2.8.0; extra == "jwt"
Provides-Extra: dev
Requires-Dist: pytest>=7.0.0; extra == "dev"
Requires-Dist: pytest-asyncio>=0.21.0; extra == "dev"
